odoo/addons/l10n_it_account_stamp/README.rst
odoo/addons/l10n_it_account_stamp/__init__.py
odoo/addons/l10n_it_account_stamp/__manifest__.py
odoo/addons/l10n_it_account_stamp/data/data.xml
odoo/addons/l10n_it_account_stamp/i18n/it.po
odoo/addons/l10n_it_account_stamp/i18n/l10n_it_account_stamp.pot
odoo/addons/l10n_it_account_stamp/migrations/18.0.1.0.0/noupdate_changes.xml
odoo/addons/l10n_it_account_stamp/migrations/18.0.1.0.0/post-migration.py
odoo/addons/l10n_it_account_stamp/migrations/18.0.1.0.0/pre-migration.py
odoo/addons/l10n_it_account_stamp/migrations/18.0.1.1.0/post-migration.py
odoo/addons/l10n_it_account_stamp/models/__init__.py
odoo/addons/l10n_it_account_stamp/models/account_move.py
odoo/addons/l10n_it_account_stamp/models/company.py
odoo/addons/l10n_it_account_stamp/models/product.py
odoo/addons/l10n_it_account_stamp/readme/CONFIGURE.md
odoo/addons/l10n_it_account_stamp/readme/CONTRIBUTORS.md
odoo/addons/l10n_it_account_stamp/readme/DESCRIPTION.md
odoo/addons/l10n_it_account_stamp/readme/ROADMAP.md
odoo/addons/l10n_it_account_stamp/readme/USAGE.md
odoo/addons/l10n_it_account_stamp/static/description/icon.png
odoo/addons/l10n_it_account_stamp/static/description/index.html
odoo/addons/l10n_it_account_stamp/tests/__init__.py
odoo/addons/l10n_it_account_stamp/tests/test_account_stamp_invoicing.py
odoo/addons/l10n_it_account_stamp/views/account_move_report.xml
odoo/addons/l10n_it_account_stamp/views/account_move_view.xml
odoo/addons/l10n_it_account_stamp/views/company_view.xml
odoo/addons/l10n_it_account_stamp/views/product_view.xml
odoo_addon_l10n_it_account_stamp-18.0.1.2.0.2.dist-info/METADATA
odoo_addon_l10n_it_account_stamp-18.0.1.2.0.2.dist-info/WHEEL
odoo_addon_l10n_it_account_stamp-18.0.1.2.0.2.dist-info/top_level.txt
odoo_addon_l10n_it_account_stamp-18.0.1.2.0.2.dist-info/RECORD
