Metadata-Version: 2.1
Name: odoo-addon-l10n_it_account_stamp
Version: 18.0.1.2.0.2
Requires-Python: >=3.10
Requires-Dist: odoo==18.0.*
Summary: Gestione automatica dell'imposta di bollo
Home-page: https://github.com/OCA/l10n-italy
License: LGPL-3
Author: Ermanno Gnan, Sergio Corato, Enrico Ganzaroli, Odoo Community Association (OCA)
Author-email: support@odoo-community.org
Classifier: Programming Language :: Python
Classifier: Framework :: Odoo
Classifier: Framework :: Odoo :: 18.0
Classifier: License :: OSI Approved :: GNU Lesser General Public License v3 (LGPLv3)
